dbwebform/__init__.py
dbwebform/app.py
dbwebform/favicon.png
dbwebform/static/dbwebform/index.d.ts
dbwebform/static/dbwebform/index.d.ts.map
dbwebform/static/dbwebform/index.js
dbwebform/static/dbwebform/index.js.map
dbwebform/templates/dbwebform/base.html
dbwebform/templates/dbwebform/index.html
dbwebform-1.0.1.dist-info/licenses/LICENSE
dbwebform-1.0.1.dist-info/METADATA
dbwebform-1.0.1.dist-info/WHEEL
dbwebform-1.0.1.dist-info/top_level.txt
dbwebform-1.0.1.dist-info/RECORD
