Metadata-Version: 2.4
Name: dbwebform
Version: 1.0.1
Summary: Flask-based web forms for database models with auto-generated forms and admin interface
Home-page: https://github.com/MagIlyasDOMA/dbwebform
Author: Маг Ильяс DOMA (MagIlyasDOMA)
Author-email: magilyas.doma.09@list.ru
License: MIT
Project-URL: Documentation, https://github.com/MagIlyasDOMA/dbwebform/README.md
Project-URL: Source, https://github.com/MagIlyasDOMA/dbwebform
Project-URL: Tracker, https://github.com/MagIlyasDOMA/dbwebform/issues
Keywords: flask,web-forms,database,sqlalchemy,wtforms
Classifier: Development Status :: 5 - Production/Stable
Classifier: Environment :: Web Environment
Classifier: Framework :: Flask
Classifier: Intended Audience :: Developers
Classifier: Intended Audience :: System Administrators
Classifier: Intended Audience :: Information Technology
Classifier: License :: OSI Approved :: MIT License
Classifier: Operating System :: OS Independent
Classifier: Programming Language :: Python :: 3
Classifier: Programming Language :: Python :: 3.8
Classifier: Programming Language :: Python :: 3.9
Classifier: Programming Language :: Python :: 3.10
Classifier: Programming Language :: Python :: 3.11
Classifier: Programming Language :: Python :: 3.12
Classifier: Programming Language :: Python :: 3.13
Classifier: Programming Language :: Python :: 3.14
Classifier: Topic :: Internet :: WWW/HTTP :: Dynamic Content
Classifier: Topic :: Software Development :: Libraries :: Python Modules
Classifier: Topic :: Database :: Front-Ends
Requires-Python: >=3.8
License-File: LICENSE
Requires-Dist: flask<4.0.0,>=3.1.1
Requires-Dist: sqlalchemy<3.0.0,>=2.0.44
Requires-Dist: flask-sqlalchemy<4.0.0,>=3.1.1
Requires-Dist: flask-wtf<2.0.0,>=1.2.2
Requires-Dist: wtforms<4.0.0,>=3.2.1
Requires-Dist: hrenpack<=3.0.0,>=2.2.2
Requires-Dist: db-model-generator<=2.0.0,>=1.5.1
Dynamic: author
Dynamic: author-email
Dynamic: classifier
Dynamic: description
Dynamic: description-content-type
Dynamic: home-page
Dynamic: keywords
Dynamic: license
Dynamic: license-file
Dynamic: project-url
Dynamic: requires-dist
Dynamic: requires-python
Dynamic: summary
